laaiutils/__init__.py
laaiutils/dictionary/__init__.py
laaiutils-1.0.2.dist-info/METADATA
laaiutils-1.0.2.dist-info/WHEEL
laaiutils-1.0.2.dist-info/top_level.txt
laaiutils-1.0.2.dist-info/RECORD
