Metadata-Version: 2.1
Name: laaiutils
Version: 1.0.2
Summary: Useful utils
Home-page: https://github.com/ketu/laaiutils
Author: ketu.lai
Author-email: ketu.lai@gmail.com
License: MIT
Keywords: utils
Platform: UNKNOWN
Requires-Python: >=3.5
